wiba/__init__.py
wiba-0.2.3.dist-info/METADATA
wiba-0.2.3.dist-info/WHEEL
wiba-0.2.3.dist-info/entry_points.txt
wiba-0.2.3.dist-info/top_level.txt
wiba-0.2.3.dist-info/RECORD
