Metadata-Version: 2.4
Name: wiba
Version: 0.2.3
Summary: Official Python client library for WIBA argument mining API
Home-page: https://github.com/WIBA-ORG/wiba-python-client
Author: WIBA Research Team
Author-email: WIBA Research Team <airan002@ucr.edu>
Maintainer-email: Arman Irani <airan002@ucr.edu>
License: MIT
Project-URL: Homepage, https://wiba.dev
Project-URL: Documentation, https://wiba.dev/docs
Project-URL: Repository, https://github.com/WIBA-ORG/wiba-python-client
Project-URL: Bug Reports, https://github.com/WIBA-ORG/wiba-python-client/issues
Keywords: argument mining,natural language processing,nlp,text analysis,computational argumentation,topic extraction,stance detection
Classifier: Development Status :: 4 - Beta
Classifier: Intended Audience :: Developers
Classifier: Intended Audience :: Science/Research
Classifier: License :: OSI Approved :: MIT License
Classifier: Operating System :: OS Independent
Classifier: Programming Language :: Python :: 3
Classifier: Programming Language :: Python :: 3.8
Classifier: Programming Language :: Python :: 3.9
Classifier: Programming Language :: Python :: 3.10
Classifier: Programming Language :: Python :: 3.11
Classifier: Programming Language :: Python :: 3.12
Classifier: Topic :: Scientific/Engineering :: Artificial Intelligence
Classifier: Topic :: Text Processing :: Linguistic
Requires-Python: >=3.8
Requires-Dist: requests>=2.25.0
Requires-Dist: pandas>=1.2.0
Requires-Dist: numpy>=1.19.0
Requires-Dist: tqdm>=4.50.0
Requires-Dist: structlog>=21.1.0
Provides-Extra: dev
Requires-Dist: pytest>=7.0.0; extra == "dev"
Requires-Dist: pytest-asyncio>=0.21.0; extra == "dev"
Requires-Dist: black>=23.0.0; extra == "dev"
Requires-Dist: isort>=5.12.0; extra == "dev"
Requires-Dist: flake8>=6.0.0; extra == "dev"
Requires-Dist: mypy>=1.0.0; extra == "dev"
Provides-Extra: docs
Requires-Dist: sphinx>=5.0.0; extra == "docs"
Requires-Dist: sphinx-rtd-theme>=1.2.0; extra == "docs"
Requires-Dist: myst-parser>=1.0.0; extra == "docs"
Dynamic: author
Dynamic: home-page
Dynamic: requires-python
